Metadata-Version: 2.1
Name: statbasket
Version: 1.0.0
Summary: A small statistics package for data science students and enthusiasts
Home-page: https://github.com/chumbie/statbasket
Author: John Weldon
Author-email: john.weldon117@gmail.com
License: MIT
Download-URL: https://github.com/chumbie/statbasket/archive/refs/tags/v_01.0.0.tar.gz
Keywords: statistics,data-science,students,lite,pure-python
Platform: UNKNOWN
Classifier: Development Status :: 5 - Production/Stable
Classifier: Intended Audience :: Developers
Classifier: Topic :: Software Development :: Build Tools
Classifier: License :: OSI Approved :: MIT License
Classifier: Programming Language :: Python :: 3.6
License-File: LICENSE
